README.md
setup.py
rsshub/__init__.py
rsshub/config.py
rsshub/extensions.py
rsshub/google_analytics.py
rsshub/rssreborn.py
rsshub/utils.py
rsshub/blueprints/__init__.py
rsshub/blueprints/main.py
rsshub/rssfeeder/__init__.py
rsshub/rssfeeder/ai.py
rsshub/rssfeeder/rss.py
rsshub/rssfeeder/utils.py
rsshub/rssfeeder/store/__init__.py
rsshub/rssfeeder/store/dbs.py
rsshub/spiders/__init__.py
rssreborn.egg-info/PKG-INFO
rssreborn.egg-info/SOURCES.txt
rssreborn.egg-info/dependency_links.txt
rssreborn.egg-info/entry_points.txt
rssreborn.egg-info/requires.txt
rssreborn.egg-info/top_level.txt
tests/__init__.py
tests/base.py
tests/test_cli.py
tests/test_errors.py
tests/test_main.py
tests/test_source.py