Metadata-Version: 2.1
Name: rssreborn
Version: 0.1.1
Summary: Make RSS great again!
Home-page: https://github.com/lucasjinreal/RSSReborn
Author: Open Jarvis AI
